chatdoctor/__init__.py
chatdoctor-0.0.1.dev0.dist-info/METADATA
chatdoctor-0.0.1.dev0.dist-info/WHEEL
chatdoctor-0.0.1.dev0.dist-info/top_level.txt
chatdoctor-0.0.1.dev0.dist-info/RECORD
