Metadata-Version: 2.1
Name: chatdoctor
Version: 0.0.1.dev0
Summary: chatdoctor - A Medical Chat Model Fine-tuned on LLaMA Model using Medical Domain Knowledge
Author: Shadow Walker
License: UNKNOWN
Keywords: chatdoctor
Platform: UNKNOWN
Classifier: Programming Language :: Python :: 3
Classifier: Programming Language :: Python :: 3.8
Classifier: Programming Language :: Python :: 3.9
Classifier: Programming Language :: Python :: 3.10
Requires-Dist: torch
